[
  {
    "title": "Data analyst",
    "description": "My primary portfolio website showcasing projects, skills, and experience.",
    "url": "https://dar-ishfaq-1.github.io/my_portfolio/",
    "category": "Portfolio"
  },
  {
    "title": "backend",
    "description": "Backend development portfolio highlighting server-side projects and API work.",
    "url": "https://darashfaqdev.github.io/MyPortfolioWebSite/",
    "category": "Backend"
  },
  {
    "title": "Mubarakh Soob Portfolio",
    "description": "Client portfolio project for Mubarakh Soob.",
    "url": "https://darashfaqdev.github.io/Mubarakh-Soob-Portfolio/",
    "category": "Projects"
  }
]
